pyautoppt/__init__.py
pyautoppt-0.1.1.dist-info/WHEEL
pyautoppt-0.1.1.dist-info/METADATA
pyautoppt-0.1.1.dist-info/RECORD
