Metadata-Version: 2.1
Name: pyautoppt
Version: 0.1.1
Summary: 这是一个简单的 PPT 自动化
Home-page: https://python-poetry.org/
Keywords: ppt
Author: wn0x00
Author-email: 320753691@qq.com
Requires-Python: >=3.7,<4.0
Classifier: Programming Language :: Python :: 3
Classifier: Programming Language :: Python :: 3.10
Classifier: Programming Language :: Python :: 3.7
Classifier: Programming Language :: Python :: 3.8
Classifier: Programming Language :: Python :: 3.9
Requires-Dist: pywin32 (>=304,<305)
Project-URL: Documentation, https://github.com/wn0x00/pyautoppt
Project-URL: Repository, https://github.com/wn0x00/pyautoppt
